ironman/__init__.py
ironman/ironman.py
ironman_package-1.1.0.dist-info/LICENSE
ironman_package-1.1.0.dist-info/METADATA
ironman_package-1.1.0.dist-info/WHEEL
ironman_package-1.1.0.dist-info/top_level.txt
ironman_package-1.1.0.dist-info/RECORD
