Metadata-Version: 2.2
Name: ironman-package
Version: 1.1.0
Summary: Joint fit Rossiter-McLaughlin data with photometry and out-of-transit radial velocities
Home-page: https://github.com/jiespinozar/ironman
Author: Juan Ignacio Espinoza-Retamal
Author-email: jiespinozar@uc.cl
License: MIT
Keywords: Astronomy,Obliquities,Radial Velocities
Classifier: Programming Language :: Python :: 3
Classifier: License :: OSI Approved :: MIT License
Classifier: Operating System :: OS Independent
Classifier: Topic :: Scientific/Engineering :: Astronomy
Requires-Python: >=3.6
License-File: LICENSE
Requires-Dist: numpy
Requires-Dist: scipy
Requires-Dist: pandas
Requires-Dist: batman-package
Requires-Dist: dynesty
Requires-Dist: astropy
Requires-Dist: rmfit>=1.0.2
Requires-Dist: tqdm
Dynamic: author
Dynamic: author-email
Dynamic: classifier
Dynamic: description
Dynamic: description-content-type
Dynamic: home-page
Dynamic: keywords
Dynamic: license
Dynamic: requires-dist
Dynamic: requires-python
Dynamic: summary
